examples/data_preprocess.py
examples/fl.py
examples/train_helloworld.py
examples/workflow01.py
jcweaver/__init__.py
jcweaver/adapter/BaseAdapter.py
jcweaver/adapter/__init__.py
jcweaver/adapter/modelarts.py
jcweaver/adapter/octopus.py
jcweaver/adapter/openi.py
jcweaver/api/__init__.py
jcweaver/api/api.py
jcweaver/api/decorators.py
jcweaver/core/__init__.py
jcweaver/core/const.py
jcweaver/core/context.py
jcweaver/core/logger.py
jcweaver/core/metadata.py
jcweaver/core/registry.py
jcweaver/core/schema.py
jcweaver/core/nodes/__init__.py
jcweaver/core/nodes/base_node.py
jcweaver/core/nodes/bind_node.py
jcweaver/core/nodes/data_return_node.py
jcweaver/core/nodes/end_node.py
jcweaver/core/nodes/start_node.py
jcweaver/core/nodes/train_node.py
jcweaver/core/utils/args_mapping.py
jcweaver/tests/decorator_test.py
jcweaver/tests/input_test.py
jcweaver/tests/io_test.py
jcweaver/tests/node_test.py
jcweaver/tests/node_test2.py
jcweaver/tests/node_test3.py
jcweaver/tests/node_test4.py
jcweaver/tests/node_test5.py
jcweaver/tests/output_test.py
jcweaver/tests/split_test.py
jcweaver-0.1.8.dist-info/METADATA
jcweaver-0.1.8.dist-info/WHEEL
jcweaver-0.1.8.dist-info/top_level.txt
jcweaver-0.1.8.dist-info/RECORD
